setup.py
OutputLilyPond.egg-info/PKG-INFO
OutputLilyPond.egg-info/SOURCES.txt
OutputLilyPond.egg-info/dependency_links.txt
OutputLilyPond.egg-info/requires.txt
OutputLilyPond.egg-info/top_level.txt
outputlilypond/__init__.py
outputlilypond/__main__.py
outputlilypond/functions.py
outputlilypond/problems.py
outputlilypond/settings.py